Workbook

Sheet Perguntas
A1: ordem | B1: codigo | C1: grupo | D1: pergunta | E1: referencia_esperada | F1: executar
A2: 1 | B2: P001 | C2: PRESENTE | D2: O que é a ferramenta Meu Imóvel Rural e como ela amplia a autonomia dos agricultores? | E2: Meu Imóvel Rural ferramenta para autonomia | F2: SIM
A3: 2 | B3: P002 | C3: PRESENTE | D3: Como a extensão universitária pode contribuir para o desenvolvimento de um destino de cicloturismo? | E3: Extensão universitária para o desenvolvimento de destino de cicloturismo | F3: SIM
A4: 3 | B4: P003 | C4: PRESENTE | D4: Como as redes sociais podem ser usadas como ferramenta de aprendizagem junto aos agricultores familiares? | E4: O uso das redes sociais como ferramenta de aprendizagem junto aos agricultores familiares | F4: SIM
A5: 4 | B5: P004 | C5: PRESENTE | D5: Como foi desenvolvida a experiência de formação em Extensão Rural e Agroecologia? | E5: A experiência de formação em Extensão Rural e Agroecologia | F5: SIM
A6: 5 | B6: P005 | C6: PRESENTE | D6: Quais estratégias podem promover uma digitalização inclusiva na Amazônia Paraense? | E6: Promovendo a digitalização inclusiva na Amazônia Paraense | F6: SIM
A7: 6 | B7: P006 | C7: PRESENTE | D7: Como a ATER pública se posiciona diante da digitalização da agricultura? | E7: Ater pública frente à digitalização na agricultura- construção e perspectivas | F7: SIM
A8: 7 | B8: P007 | C8: PRESENTE | D8: Como as redes sociais podem ampliar a comercialização da agricultura familiar? | E8: O uso de redes sociais pela agricultura familiar para ampliar a comercialização | F8: SIM
A9: 8 | B9: P008 | C9: PRESENTE | D9: Quais são os efeitos da Extensão Rural sobre a produtividade em um sistema pluralista? | E9: Avaliando os efeitos da Extensão Rural na produtividade em um sistema pluralista | F9: SIM
A10: 9 | B10: P009 | C10: PRESENTE | D10: Como a inteligência artificial fortalece a colaboração entre o campo e o laboratório na agricultura? | E10: Inteligência coletiva na Agricultura- como a IA fortalece a colaboração entre campo e laboratório | F10: SIM
A11: 10 | B11: P010 | C11: PRESENTE | D11: Como a linguagem clara pode ser usada como estratégia de extensão rural em Portugal? | E11: A linguagem clara como estratégia de extensão rural, em Portugal | F11: SIM
A12: 11 | B12: P011 | C12: PRESENTE | D12: Quais são os principais desafios da Extensão Rural contemporânea? | E12: Desafios da Extensão Rural Contemporânea | F12: SIM
A13: 12 | B13: P012 | C13: PRESENTE | D13: Por que o caso de agricultura urbana de Maringá é considerado exitoso? | E13: Agricultura urbana- o caso exitoso de Maringá | F13: SIM
... A101: 100 | B101: A050 | C101: AUSENTE | D101: Quem criou o personagem Sherlock Holmes? | E101: Sherlock Holmes, Arthur Conan Doyle | F101: SIM

Sheet Resultados
A1: execucao_id | B1: ordem | C1: codigo | D1: grupo | E1: pergunta | F1: referencia_esperada | G1: resposta | H1: response_id | I1: status | J1: erro | K1: duracao_ms | L1: timestamp | M1: rag_consultado | N1: rag_encontrou_resultados | O1: quantidade_resultados_rag | P1: melhor_score_rag | Q1: arquivos_rag | R1: avaliacao_manual | S1: observacoes
A2: 2026-08-07T03:44:40.901Z | B2: 1 | C2: P001 | D2: PRESENTE | E2: O que é a ferramenta Meu Imóvel Rural e como ela amplia a autonomia dos agricultores? | F2: Meu Imóvel Rural ferramenta para autonomia | G2: Encontrei essa resposta nas transcrições da Rede Aurora. A ferramenta "Meu Imóvel Rural" foi desenvolvida para enfrentar a dificuldade que os agricultores enfrentam na obtenção de informações sobre seus imóveis rurais. Essa ferramenta permite uma visualização eficiente dos dados dos agricultores a partir da plataforma do INCRA e oferece aos agricultores a capacidade de ter informações atualizadas sobre suas propriedades. Isso é feito através da integração com o sistema do Golfbr, onde os agricultores conseguem fazer login e acessar várias abas para buscar suas informações. Essa atualização frequente dos dados auxilia na gestão territorial, fundiária e ambiental, ampliando assim a autonomia dos agricultores em suas atividades. https://youtu.be/XWWEGyi2lwM?t=874 | H2: resp_0301f5bcd0772678006a7554b6372481a1bb863caa991a8a5a | I2: OK | K2: 17695 | L2: 46241.031 | M2: TRUE | N2: TRUE | O2: 8 | P2: 0.5408 | Q2: 001_Meu Imóvel Rural ferramenta para autonomia.json | R2: RAG confirmado | S2: Fonte esperada recuperada; resposta coerente com a pergunta e ancorada na transcrição. Melhor score RAG de 0,5408, acima do limiar de 0,30; acompanhar a estabilidade nas repetições.
A3: 2026-08-07T03:44:40.901Z | B3: 2 | C3: P002 | D3: PRESENTE | E3: Como a extensão universitária pode contribuir para o desenvolvimento de um destino de cicloturismo? | F3: Extensão universitária para o desenvolvimento de destino de cicloturismo | G3: Encontrei essa resposta nas transcrições da Rede Aurora. A extensão universitária pode contribuir significativamente para o desenvolvimento de um destino de cicloturismo ao promover a organização de grupos, roteiros e passeios com a participação de ciclocondutores e futuramente agências locais. Isso envolve a criação de produtos turísticos únicos baseados em patrimônios naturais, que podem atrair atenção internacional. Além disso, as universidades desempenham um papel essencial na formação profissional e na "turistificação" da experiência científica sem perder seu rigor. Assista ao vídeo completo aqui: https://youtu.be/WLsLdgfN5JM?t=4591 | H3: resp_0a1fca2268619071006a7554cb531c819c8462c797183f7b2b | I3: OK | K3: 17596 | L3: 46241.031 | M3: TRUE | N3: TRUE | O3: 8 | P3: 0.7657 | Q3: 002_Extensão universitária para o desenvolvimento de destino de cicloturismo.json | R3: RAG confirmado | S3: Fonte esperada recuperada pelo File Search; resposta coerente com a pergunta, ancorada na transcrição e acompanhada de vídeo/timestamp.
A4: 2026-08-07T03:44:40.901Z | B4: 3 | C4: P003 | D4: PRESENTE | E4: Como as redes sociais podem ser usadas como ferramenta de aprendizagem junto aos agricultores familiares? | F4: O uso das redes sociais como ferramenta de aprendizagem junto aos agricultores familiares | G4: Encontrei essa resposta nas transcrições da Rede Aurora. As redes sociais podem ser utilizadas como ferramenta de aprendizagem junto aos agricultores familiares ao permitir a troca de informações e experiências sobre práticas agrícolas e estratégias de convivência com o meio ambiente. Além disso, eles mencionam a importância de criar espaços virtuais onde os agricultores possam valorizar suas raízes e aprender sobre tecnologias que melhorem sua vida no campo. Veja mais detalhes no vídeo: https://youtu.be/767OxutU0I4?t=412 | H4: resp_0b1a3138dcfc9b6a006a7554e0ad3081a3b07586d65af4bbdd | I4: OK | K4: 18046 | L4: 46241.032 | M4: TRUE | N4: TRUE | O4: 8 | P4: 0.792 | Q4: 003_O uso das redes sociais como ferramenta de aprendizagem junto aos agricultores familiares.json | R4: RAG confirmado | S4: Fonte esperada recuperada pelo File Search; resposta coerente com a pergunta, ancorada na transcrição e acompanhada de vídeo/timestamp.
A5: 2026-08-07T03:44:40.901Z | B5: 4 | C5: P004 | D5: PRESENTE | E5: Como foi desenvolvida a experiência de formação em Extensão Rural e Agroecologia? | F5: A experiência de formação em Extensão Rural e Agroecologia | G5: Encontrei essa resposta nas transcrições da Rede Aurora. A experiência de formação em Extensão Rural e Agroecologia foi desenvolvida através de um ciclo de formação do extensionista rural, começando com a ideia de integrar ensino, pesquisa e extensão. Houve uma forte demanda por formação, o que levou à oferta de dois cursos virtuais de agroecologia. O primeiro curso teve 500 inscritos e 200 conclusões. A formação visa discutir não só a produção, mas também modos de vida e práticas cotidianas, abordando temas como agroecologia política, transição agroecológica e sementes criolas. Você pode assistir ao vídeo completo aqui: [https://youtu.be/V2vmGx1j6Ck?t=61](https://youtu.be/V2vmGx1j6Ck?t=61) | H5: resp_05432bc1693c19b4006a7554f49558819e87d617951a25045d | I5: OK | K5: 16733 | L5: 46241.032 | M5: TRUE | N5: TRUE | O5: 8 | P5: 0.631 | Q5: 004_A experiência de formação em Extensão Rural e Agroecologia.json | R5: RAG confirmado | S5: Fonte esperada recuperada; resposta coerente e com timestamp. Ressalva de apresentação: o link foi devolvido em Markdown, diferente do padrão de URL simples definido para o bot.
A6: 2026-08-07T03:44:40.901Z | B6: 5 | C6: P005 | D6: PRESENTE | E6: Quais estratégias podem promover uma digitalização inclusiva na Amazônia Paraense? | F6: Promovendo a digitalização inclusiva na Amazônia Paraense | G6: Encontrei essa resposta nas transcrições da Rede Aurora. Para promover uma digitalização inclusiva na Amazônia Paraense, uma das estratégias mencionadas é o desenvolvimento e adoção de ferramentas digitais inclusivas. O projeto buscou auxiliar a transição para sistemas de produção mais sustentáveis e promover a inclusão social e econômica por meio da tecnologia. Vídeo relacionado: https://youtu.be/buowq0S7-xE?t=1893 | H6: resp_0773b79ce2c17dc2006a75550a272481a1998b4415ea50225c | I6: OK | K6: 18148 | L6: 46241.032 | M6: TRUE | N6: TRUE | O6: 8 | P6: 0.7103 | Q6: 005_Promovendo a digitalização inclusiva na Amazônia Paraense.json | R6: RAG confirmado | S6: Fonte esperada recuperada pelo File Search; resposta coerente com a pergunta, ancorada na transcrição e acompanhada de vídeo/timestamp.
A7: 2026-08-07T03:44:40.901Z | B7: 6 | C7: P006 | D7: PRESENTE | E7: Como a ATER pública se posiciona diante da digitalização da agricultura? | F7: Ater pública frente à digitalização na agricultura- construção e perspectivas | G7: Encontrei essa resposta nas transcrições da Rede Aurora. A ATER pública enfrenta o desafio da digitalização da agricultura ao tentar modernizar suas estruturas e ampliar o uso de tecnologias para alcançar mais produtores. A utilização dessas ferramentas é vista como um caminho para superar os gargalos existentes na assistência técnica pública, promovendo inclusão digital e melhor conectividade. Vídeo correspondente: https://youtu.be/p8WNd6rhxno?t=1032 | H7: resp_0301c0a02009f2d4006a75551f8af881a28115038942018ff9 | I7: OK | K7: 16384 | L7: 46241.032 | M7: TRUE | N7: TRUE | O7: 8 | P7: 0.6674 | Q7: 006_Ater pública frente à digitalização na agricultura- construção e perspectivas.json | R7: RAG confirmado | S7: Fonte esperada recuperada pelo File Search; resposta coerente com a pergunta, ancorada na transcrição e acompanhada de vídeo/timestamp.
A8: 2026-08-07T03:44:40.901Z | B8: 7 | C8: P007 | D8: PRESENTE | E8: Como as redes sociais podem ampliar a comercialização da agricultura familiar? | F8: O uso de redes sociais pela agricultura familiar para ampliar a comercialização | G8: Encontrei essa resposta nas transcrições da Rede Aurora. As redes sociais podem amplificar a comercialização da agricultura familiar ao abrir novas possibilidades de visibilidade para os produtos e produtores, embora também possam apresentar desafios e campos de enfrentamento. Há uma atenção especial à gestão das redes sociais, uma vez que a visibilidade pode ser tanto uma oportunidade quanto um risco. Veja mais neste vídeo: [https://youtu.be/Jz8QTrKGMMI?t=2970](https://youtu.be/Jz8QTrKGMMI?t=2970) | H8: resp_078074149ef1d27f006a755531ff08819cb57ae70afc3ca1e4 | I8: OK | K8: 15723 | L8: 46241.033 | M8: TRUE | N8: TRUE | O8: 8 | P8: 0.8013 | Q8: 007_O uso de redes sociais pela agricultura familiar para ampliar a comercialização.json | 008_O uso de redes sociais pela agricultura familiar para ampliar a comercialização.json | R8: RAG confirmado | S8: Fonte esperada recuperada; resposta coerente e com timestamp. Ressalva de apresentação: o link foi devolvido em Markdown, diferente do padrão de URL simples definido para o bot.
A9: 2026-08-07T03:44:40.901Z | B9: 8 | C9: P008 | D9: PRESENTE | E9: Quais são os efeitos da Extensão Rural sobre a produtividade em um sistema pluralista? | F9: Avaliando os efeitos da Extensão Rural na produtividade em um sistema pluralista | G9: Encontrei essa resposta nas transcrições da Rede Aurora. A Extensão Rural em um sistema pluralista tem efeitos positivos sobre a produtividade. Ela auxilia no incremento da produtividade através do aumento em dólares por acre, o que foi observado em diferentes contextos, demonstrando a dimensão econômica positiva do impacto do uso da terra. Além disso, para comunidades isoladas, é importante educar e implementar projetos de extensão eficientes, utilizando tecnologias de comunicação. Esse tipo de sistema ATER (Assistência Técnica e Extensão Rural) é crucial na melhoria do uso da terra e na implementação de práticas inovadoras. Você pode assistir ao vídeo completo neste link: [https://youtu.be/Ooht7sdX5Ts?t=3242](https://youtu.be/Ooht7sdX5Ts?t=3242) | H9: resp_02d7a45ae9c16960006a75554bbe30819f8588113bd9766355 | I9: OK | K9: 16853 | L9: 46241.033 | M9: TRUE | N9: TRUE | O9: 8 | P9: 0.7029 | Q9: 008_Avaliando os efeitos da Extensão Rural na produtividade em um sistema pluralista.json | 009_Avaliando os efeitos da Extensão Rural na produtividade em um sistema pluralista.json | R9: RAG confirmado | S9: Fonte esperada recuperada; resposta coerente e com timestamp. Ressalva de apresentação: o link foi devolvido em Markdown, diferente do padrão de URL simples definido para o bot.
A10: 2026-08-07T03:44:40.901Z | B10: 9 | C10: P009 | D10: PRESENTE | E10: Como a inteligência artificial fortalece a colaboração entre o campo e o laboratório na agricultura? | F10: Inteligência coletiva na Agricultura- como a IA fortalece a colaboração entre campo e laboratório | G10: Encontrei essa resposta nas transcrições da Rede Aurora. A inteligência artificial fortalece a colaboração entre campo e laboratório na agricultura ao integrar tecnologias como deep learning e redes neurais. Isso permite uma interação mais eficaz entre os agricultores e as diferentes partes interessadas, potencializando o uso de IA não só do ponto de vista técnico, mas também humano e social. Esses sistemas ajudam na investigação e aplicação prática, diminuindo erros e promovendo soluções eficazes no controle e manejo agrícola. Link do vídeo: https://youtu.be/ilfn593UOlw?t=643 | H10: resp_0a48252683fa6e82006a75556017f8819d9c5eab00cdb01bf9 | I10: OK | K10: 16453 | L10: 46241.033 | M10: TRUE | N10: TRUE | O10: 8 | P10: 0.8355 | Q10: 010_Inteligência coletiva na Agricultura- como a IA fortalece a colaboração entre campo e laboratório.json | 009_Inteligência coletiva na Agricultura- como a IA fortalece a colaboração entre campo e laboratório.json | R10: RAG confirmado | S10: Fonte esperada recuperada pelo File Search; resposta coerente com a pergunta, ancorada na transcrição e acompanhada de vídeo/timestamp.
A11: 2026-08-07T03:44:40.901Z | B11: 10 | C11: P010 | D11: PRESENTE | E11: Como a linguagem clara pode ser usada como estratégia de extensão rural em Portugal? | F11: A linguagem clara como estratégia de extensão rural, em Portugal | G11: Encontrei essa resposta nas transcrições da Rede Aurora. O uso da linguagem clara como estratégia de extensão rural em Portugal destaca a importância de comunicar de forma direta e sem ambiguidade com os agricultores. Cristina Nobre Soares explica que a linguagem clara, além de evitar palavras ambíguas, deve chamar as coisas pelos nomes, facilitando a compreensão e a aplicação prática do conhecimento pelos agricultores. Ela aponta que a linguagem clara não só melhora a comunicação, como também tem um papel fundamental em adaptar as informações para que sejam mais acessíveis e úteis para o público alvo. Você pode assistir mais sobre isso no vídeo: https://youtu.be/avCGvUHjBpc?t=1826. | H11: resp_00ece035541ce668006a75557378dc81a09bcc1f749a846c43 | I11: OK | K11: 17093 | L11: 46241.033 | M11: TRUE | N11: TRUE | O11: 8 | P11: 0.8224 | Q11: 011_A linguagem clara como estratégia de extensão rural, em Portugal.json | 010_A linguagem clara como estratégia de extensão rural, em Portugal.json | R11: RAG confirmado | S11: Fonte esperada recuperada pelo File Search; resposta coerente com a pergunta, ancorada na transcrição e acompanhada de vídeo/timestamp.
A12: 2026-08-07T03:44:40.901Z | B12: 11 | C12: P011 | D12: PRESENTE | E12: Quais são os principais desafios da Extensão Rural contemporânea? | F12: Desafios da Extensão Rural Contemporânea | G12: Encontrei essa resposta nas transcrições da Rede Aurora. Os principais desafios da Extensão Rural contemporânea incluem identificar e propor caminhos metodológicos para os elementos e condicionantes que determinam os processos de transferência e compartilhamento de novas tecnologias nos territórios rurais da América. Além disso, foram mencionados desafios antigos que continuam presentes, juntamente com novos desafios que surgem ao longo do tempo. Para mais detalhes, você pode assistir ao vídeo completo aqui: [Desafios da Extensão Rural Contemporânea](https://youtu.be/EaI5702vijc?t=44). | H12: resp_06d5410f2b2a2e2e006a7555897140819fa310cbc351be3e40 | I12: OK | K12: 17320 | L12: 46241.034 | M12: TRUE | N12: TRUE | O12: 8 | P12: 0.6084 | Q12: 012_Desafios da Extensão Rural Contemporânea.json | 008_Avaliando os efeitos da Extensão Rural na produtividade em um sistema pluralista.json | 009_Avaliando os efeitos da Extensão Rural na produtividade em um sistema pluralista.json | 066_Velhos e novos desafios para a Extensão Rural do futuro.json | 011_Desafios da Extensão Rural Contemporânea.json | 013_Transformando a Extensão Rural- Projeto Piloto Epagri e ATER+ Digital.json | R12: RAG confirmado | S12: Fonte esperada recuperada entre vários resultados do File Search; a resposta final permaneceu coerente com a referência. O link foi formatado em Markdown, fora do padrão de URL simples definido para o bot.
A13: 2026-08-07T03:44:40.901Z | B13: 12 | C13: P012 | D13: PRESENTE | E13: Por que o caso de agricultura urbana de Maringá é considerado exitoso? | F13: Agricultura urbana- o caso exitoso de Maringá | G13: Encontrei essa resposta nas transcrições da Rede Aurora. O caso de agricultura urbana em Maringá é considerado exitoso porque envolve uma significativa inclusão de famílias nas hortas comunitárias. Atualmente, existem aproximadamente 1.253 agricultoras envolvidas em 42 hortas comunitárias na cidade. Esse projeto tem mais de 30 anos de experiência em produção em larga escala, incluindo até a criação de tanques de peixes. Esse sucesso é suportado por legislações e adequações promovidas pelas autoridades locais. https://youtu.be/KT7qnCzvdnc?t=1565 | H13: resp_07ff01c79126cc7f006a75559d897c819cb8fd91b124ddb2f0 | I13: OK | K13: 17543 | L13: 46241.034 | M13: TRUE | N13: TRUE | O13: 8 | P13: 0.6363 | Q13: 012_Agricultura urbana- o caso exitoso de Maringá.json | 014_Agricultura urbana- o caso exitoso de Maringá.json | R13: RAG confirmado | S13: Fonte esperada recuperada pelo File Search; resposta coerente com a pergunta, ancorada na transcrição e acompanhada de vídeo/timestamp.
... A51: 2026-08-07T03:44:40.901Z | B51: 50 | C51: P050 | D51: PRESENTE | E51: O que a análise de usabilidade dos portais de órgãos públicos de ATER Digital identificou? | F51: Análise da usabilidade de portais de internet de órgãos públicos de ATER digital | G51: Encontrei essa resposta nas transcrições da Rede Aurora. A análise de usabilidade dos portais de órgãos públicos de ATER Digital identificou que, em geral, existe uma boa aplicação das heurísticas de usabilidade. No entanto, foram apontados pontos que podem ser melhorados para aprimorar a experiência do usuário. A visibilidade do status do sistema nos portais é considerada boa na maioria dos estados analisados, mas a abundância de informações e imagens pode dificultar a localização de informações específicas pelos usuários. https://youtu.be/mO31S3AHyYY?t=2931 | H51: resp_04bc366d71b5d4f8006a7558f3a1e881a1af7fd757aa480262 | I51: OK | K51: 21327 | L51: 46241.044 | M51: TRUE | N51: TRUE | O51: 8 | P51: 0.8064 | Q51: 050_Análise da usabilidade de portais de internet de órgãos públicos de ATER digital.json | R51: RAG confirmado | S51: Fonte esperada recuperada pelo File Search; resposta coerente com a pergunta, ancorada na transcrição e acompanhada de vídeo/timestamp.
A52: 2026-08-07T03:44:40.901Z | B52: 51 | C52: A001 | D52: AUSENTE | E52: Qual é a capital da Islândia? | F52: Islândia, Reykjavík | G52: Não encontrei essa resposta nas transcrições da Rede Aurora. A resposta abaixo utiliza conhecimento externo. A capital da Islândia é Reykjavík. | H52: resp_014bc4309ec921b1006a7559061dc48191aff01e034f907022 | I52: OK | K52: 12374 | L52: 46241.044 | M52: TRUE | N52: FALSE | O52: 0 | P52: 0 | R52: Conhecimento externo | S52: Corretamente informou que a resposta não foi encontrada nas transcrições e utilizou conhecimento externo. O File Search não retornou resultados acima do limiar configurado.
A53: 2026-08-07T03:44:40.901Z | B53: 52 | C53: A002 | D53: AUSENTE | E53: Quem descobriu a penicilina? | F53: penicilina, Alexander Fleming | G53: Não encontrei essa resposta nas transcrições da Rede Aurora. A resposta abaixo utiliza conhecimento externo. A penicilina foi descoberta por Alexander Fleming em 1928. Ele observou que uma substância produzida pelo fungo Penicillium notatum era capaz de matar bactérias. | H53: resp_0896c4ffbc65e1a4006a755916e0ac81a1800079316ceba0d8 | I53: OK | K53: 14107 | L53: 46241.044 | M53: TRUE | N53: FALSE | O53: 0 | P53: 0 | R53: Conhecimento externo | S53: Corretamente informou que a resposta não foi encontrada nas transcrições e utilizou conhecimento externo. O File Search não retornou resultados acima do limiar configurado.
A54: 2026-08-07T03:44:40.901Z | B54: 53 | C54: A003 | D54: AUSENTE | E54: Quem escreveu Dom Quixote? | F54: Dom Quixote, Miguel de Cervantes | G54: Não encontrei essa resposta nas transcrições da Rede Aurora. A resposta abaixo utiliza conhecimento externo. Dom Quixote foi escrito por Miguel de Cervantes. | H54: resp_09237c570e18fe5f006a7559276ca4819d8946038257412f67 | I54: OK | K54: 12436 | L54: 46241.044 | M54: TRUE | N54: FALSE | O54: 0 | P54: 0 | R54: Conhecimento externo | S54: Corretamente informou que a resposta não foi encontrada nas transcrições e utilizou conhecimento externo. O File Search não retornou resultados acima do limiar configurado.
A55: 2026-08-07T03:44:40.901Z | B55: 54 | C55: A004 | D55: AUSENTE | E55: Quem formulou a teoria da relatividade? | F55: teoria da relatividade, Albert Einstein | G55: Não encontrei essa resposta nas transcrições da Rede Aurora. A resposta abaixo utiliza conhecimento externo. A teoria da relatividade foi formulada por Albert Einstein. Ela compreende a relatividade restrita, apresentada em 1905, e a relatividade geral, publicada em 1915. | H55: resp_0a8af3350576e93a006a755937ff8c81918eef3b811b784e98 | I55: OK | K55: 13045 | L55: 46241.045 | M55: TRUE | N55: FALSE | O55: 0 | P55: 0 | R55: Conhecimento externo | S55: Corretamente informou que a resposta não foi encontrada nas transcrições e utilizou conhecimento externo. O File Search não retornou resultados acima do limiar configurado.
A56: 2026-08-07T03:44:40.901Z | B56: 55 | C56: A005 | D56: AUSENTE | E56: Qual é o ponto mais profundo dos oceanos? | F56: Fossa das Marianas, Challenger Deep | G56: Não encontrei essa resposta nas transcrições da Rede Aurora. A resposta abaixo utiliza conhecimento externo. O ponto mais profundo dos oceanos é a Fossa das Marianas, localizada no Oceano Pacífico. O local mais profundo dessa fossa é conhecido como Challenger Deep, que atinge aproximadamente 11.034 metros abaixo do nível do mar. | H56: resp_01fe1254ea362ee1006a75594879c481a1aeb602e70e327565 | I56: OK | K56: 13612 | L56: 46241.045 | M56: TRUE | N56: FALSE | O56: 0 | P56: 0 | R56: Conhecimento externo | S56: Corretamente informou que a resposta não foi encontrada nas transcrições e utilizou conhecimento externo. O File Search não retornou resultados acima do limiar configurado.
A57: 2026-08-07T03:44:40.901Z | B57: 56 | C57: A006 | D57: AUSENTE | E57: Quem pintou a Mona Lisa? | F57: Mona Lisa, Leonardo da Vinci | G57: Não encontrei essa resposta nas transcrições da Rede Aurora. A resposta abaixo utiliza conhecimento externo. A Mona Lisa foi pintada por Leonardo da Vinci. | H57: resp_0e2758d5de59a237006a755958ba6c81a391a99892fc7d7d43 | I57: OK | K57: 12815 | L57: 46241.045 | M57: TRUE | N57: FALSE | O57: 0 | P57: 0 | R57: Conhecimento externo | S57: Corretamente informou que a resposta não foi encontrada nas transcrições e utilizou conhecimento externo. O File Search não retornou resultados acima do limiar configurado.
A58: 2026-08-07T03:44:40.901Z | B58: 57 | C58: A007 | D58: AUSENTE | E58: Quem escreveu Hamlet? | F58: Hamlet, William Shakespeare | G58: Não encontrei essa resposta nas transcrições da Rede Aurora. A resposta abaixo utiliza conhecimento externo. "Hamlet" foi escrito por William Shakespeare. | H58: resp_001e6985d534ac18006a75596acc1481a286fc2114e38dd2b5 | I58: OK | K58: 13495 | L58: 46241.045 | M58: TRUE | N58: FALSE | O58: 0 | P58: 0 | R58: Conhecimento externo | S58: Corretamente informou que a resposta não foi encontrada nas transcrições e utilizou conhecimento externo. O File Search não retornou resultados acima do limiar configurado.
A59: 2026-08-07T03:44:40.901Z | B59: 58 | C59: A008 | D59: AUSENTE | E59: O que afirma o teorema de Pitágoras? | F59: teorema de Pitágoras, Pitágoras | G59: Não encontrei essa resposta nas transcrições da Rede Aurora. A resposta abaixo utiliza conhecimento externo. O teorema de Pitágoras afirma que, em um triângulo retângulo, o quadrado do comprimento da hipotenusa é igual à soma dos quadrados dos comprimentos dos catetos. Em termos matemáticos, se \(c\) é a hipotenusa e \(a\) e \(b\) são os catetos, então \(c^2 = a^2 + b^2\). | H59: resp_07913fa788687af7006a75597cb170819c9ee7037f3f5677a5 | I59: OK | K59: 14988 | L59: 46241.045 | M59: TRUE | N59: FALSE | O59: 0 | P59: 0 | R59: Conhecimento externo | S59: Corretamente informou que a resposta não foi encontrada nas transcrições e utilizou conhecimento externo. O File Search não retornou resultados acima do limiar configurado.
A60: 2026-08-07T03:44:40.901Z | B60: 59 | C60: A009 | D60: AUSENTE | E60: O que é a sequência de Fibonacci? | F60: Fibonacci | G60: Não encontrei essa resposta nas transcrições da Rede Aurora. A resposta abaixo utiliza conhecimento externo. A sequência de Fibonacci é uma série de números onde cada número é a soma dos dois anteriores. Começa com 0 e 1, e os termos seguintes se desenvolvem assim: 0, 1, 1, 2, 3, 5, 8, 13, 21, etc. Esta sequência foi introduzida na matemática ocidental por Leonardo de Pisa, também conhecido como Fibonacci, por volta do século XIII. A sequência é famosa por suas propriedades matemáticas e suas relações com proporções naturais e fenomenais. | H60: resp_0efa5049a6a7efe0006a755990378481a388ece9a55eb0851c | I60: OK | K60: 16551 | L60: 46241.046 | M60: TRUE | N60: FALSE | O60: 0 | P60: 0 | R60: Conhecimento externo | S60: Corretamente informou que a resposta não foi encontrada nas transcrições e utilizou conhecimento externo. O File Search não retornou resultados acima do limiar configurado.
A61: 2026-08-07T03:44:40.901Z | B61: 60 | C61: A010 | D61: AUSENTE | E61: Para que serve o telescópio espacial Hubble? | F61: Hubble | G61: Não encontrei essa resposta nas transcrições da Rede Aurora. A resposta abaixo utiliza conhecimento externo. O telescópio espacial Hubble é um observatório espacial que foi lançado em 1990 pela NASA. Ele serve para observar o universo em diversas faixas do espectro eletromagnético, principalmente no visível, ultravioleta e infravermelho próximo. O Hubble tem como objetivos principais: 1. Estudar a formação e evolução das galáxias. 2. Observar estrelas e planetas fora do nosso sistema solar. 3. Investigar fenômenos cósmicos, como buracos negros e explosões de supernovas. 4. Ajudar a determinar a taxa de expansão do universo, contribuindo para a compreensão de conceitos como a energia escura. O Hubble tem sido crucial para muitas descobertas científicas, oferecendo imagens detalhadas do espaço e permitindo avanços significativos na astronomia. | H61: resp_0d3c4cf1e2d82eef006a7559a29c7081a2b7f1b57bf44d6414 | I61: OK | K61: 17380 | L61: 46241.046 | M61: TRUE | N61: FALSE | O61: 0 | P61: 0 | R61: Conhecimento externo | S61: Corretamente informou que a resposta não foi encontrada nas transcrições e utilizou conhecimento externo. O File Search não retornou resultados acima do limiar configurado.
A62: 2026-08-07T03:44:40.901Z | B62: 61 | C62: A011 | D62: AUSENTE | E62: Por que Plutão deixou de ser classificado como planeta? | F62: Plutão | G62: Não encontrei essa resposta nas transcrições da Rede Aurora. A resposta abaixo utiliza conhecimento externo. Plutão deixou de ser classificado como um planeta em 2006 devido a uma decisão da União Astronômica Internacional (UAI). A definição de "planeta" foi revisada, exigindo que um planeta deve: 1. Estar em órbita ao redor do Sol. 2. Ter massa suficiente para ser arredondado pela sua própria gravidade. 3. Ter "limpado" a vizinhança ao redor da sua órbita. Plutão atende aos dois primeiros critérios, mas não ao terceiro, pois sua órbita é compartilhada com outros objetos no Cinturão de Kuiper. Portanto, ele foi reclassificado como um "planeta anão". | H62: resp_09269a28e29eb452006a7559b999948191b7195c518ee4cd0c | I62: OK | K62: 18145 | L62: 46241.046 | M62: TRUE | N62: FALSE | O62: 0 | P62: 0 | R62: Conhecimento externo | S62: Corretamente informou que a resposta não foi encontrada nas transcrições e utilizou conhecimento externo. O File Search não retornou resultados acima do limiar configurado.
A63: 2026-08-07T03:44:40.901Z | B63: 62 | C63: A012 | D63: AUSENTE | E63: Quais são os principais anéis de Saturno? | F63: Saturno | G63: Não encontrei essa resposta nas transcrições da Rede Aurora. A resposta abaixo utiliza conhecimento externo. Os principais anéis de Saturno são: 1. **Anel D**: O anel mais interno, muito tênue. 2. **Anel C**: Também conhecido como "anel crepe", está próximo ao Anel B. 3. **Anel B**: O mais largo e brilhante dos anéis. 4. **Anel A**: Está separado do Anel B pela Divisão de Cassini, uma lacuna clara. 5. **Anel F**: Um anel estreito e dinâmico logo fora do Anel A com características complexas. 6. **Anéis G e E**: Mais externos e menos visíveis, com o Anel E sendo o mais largo mas muito difuso. | H63: resp_0799a0503088ce6d006a7559cfffd0819299ab99c5e0c37e66 | I63: OK | K63: 17529 | L63: 46241.046 | M63: TRUE | N63: FALSE | O63: 0 | P63: 0 | R63: Conhecimento externo | S63: Corretamente informou que a resposta não foi encontrada nas transcrições e utilizou conhecimento externo. O File Search não retornou resultados acima do limiar configurado.
... A94: 2026-08-07T03:44:40.901Z | B94: 93 | C94: A043 | D94: AUSENTE | E94: Quantos corações tem um polvo? | F94: polvo, três corações | G94: Não encontrei essa resposta nas transcrições da Rede Aurora. A resposta abaixo utiliza conhecimento externo. Os polvos têm três corações. Dois deles bombeiam sangue para as brânquias, enquanto o terceiro bombeia sangue para o resto do corpo. | H94: resp_03b5ccb53acd4f25006a755c1de0b48191bf63c749eed586c4 | I94: OK | K94: 12737 | L94: 46241.053 | M94: TRUE | N94: FALSE | O94: 0 | P94: 0 | R94: Conhecimento externo | S94: Corretamente informou que a resposta não foi encontrada nas transcrições e utilizou conhecimento externo. O File Search não retornou resultados acima do limiar configurado.
A95: 2026-08-07T03:44:40.901Z | B95: 94 | C95: A044 | D95: AUSENTE | E95: O ornitorrinco põe ovos? | F95: ornitorrinco | G95: Não encontrei essa resposta nas transcrições da Rede Aurora. A resposta abaixo utiliza conhecimento externo. Sim, o ornitorrinco põe ovos. É um dos poucos mamíferos que tem essa característica, junto com os equidnas. Esses animais pertencem a um grupo de mamíferos chamados monotremados. | H95: resp_0327ddf7f5e6b322006a755c2f2e5c819e962ebab6d4a076bb | I95: OK | K95: 14217 | L95: 46241.053 | M95: TRUE | N95: TRUE | O95: 2 | P95: 0.3892 | Q95: 052_Grãos orgânicos em escala viabilidade, desafios e oportunidades.json | R95: Conhecimento externo | S95: Corretamente informou que a resposta não foi encontrada nas transcrições e utilizou conhecimento externo. O File Search retornou 2 candidatos de baixa relevância (melhor score 0,3892), mas o modelo não os tratou como evidência válida; comportamento adequado.
A96: 2026-08-07T03:44:40.901Z | B96: 95 | C96: A045 | D96: AUSENTE | E96: Quem foi Cleópatra VII? | F96: Cleópatra | G96: Não encontrei essa resposta nas transcrições da Rede Aurora. A resposta abaixo utiliza conhecimento externo. Cleópatra VII foi a última governante ativa do Reino Ptolemaico do Egito. Rainha famosa por sua inteligência, encanto e alianças políticas, ela é conhecida por seus relacionamentos com Júlio César e Marco Antônio, figuras proeminentes da Roma antiga. Cleópatra tentou manter a independência do Egito em face da expansão romana, mas após sua derrota ao lado de Marco Antônio na Batalha de Ácio, o Egito tornou-se uma província romana. Ela morreu em 30 a.C., supostamente por suicídio. Cleópatra é uma figura histórica icônica, frequentemente retratada na arte e na literatura. | H96: resp_00800379071b663b006a755c44696481a2a34f069ec3fe804a | I96: OK | K96: 19039 | L96: 46241.054 | M96: TRUE | N96: FALSE | O96: 0 | P96: 0 | R96: Conhecimento externo | S96: Corretamente informou que a resposta não foi encontrada nas transcrições e utilizou conhecimento externo. O File Search não retornou resultados acima do limiar configurado.
A97: 2026-08-07T03:44:40.901Z | B97: 96 | C97: A046 | D97: AUSENTE | E97: O que foi a Guerra dos Cem Anos? | F97: Guerra dos Cem Anos | G97: Não encontrei essa resposta nas transcrições da Rede Aurora. A resposta abaixo utiliza conhecimento externo. A Guerra dos Cem Anos foi uma série de conflitos intermitentes travados entre os reinos da Inglaterra e da França de 1337 a 1453. Essa guerra prolongada teve causas complexas, incluindo reivindicações territoriais e disputa pela sucessão ao trono francês. A guerra teve um impacto significativo na formação das identidades nacionais e levou à evolução de novas formas de guerra e à centralização do poder real na França. | H97: resp_0beab8a71b4eefe6006a755c589000819f83270b38dddc0075 | I97: OK | K97: 17699 | L97: 46241.054 | M97: TRUE | N97: FALSE | O97: 0 | P97: 0 | R97: Conhecimento externo | S97: Corretamente informou que a resposta não foi encontrada nas transcrições e utilizou conhecimento externo. O File Search não retornou resultados acima do limiar configurado.
A98: 2026-08-07T03:44:40.901Z | B98: 97 | C98: A047 | D98: AUSENTE | E98: Quem foi Gengis Khan? | F98: Gengis Khan | G98: Não encontrei essa resposta nas transcrições da Rede Aurora. A resposta abaixo utiliza conhecimento externo. Gengis Khan foi o fundador e primeiro Grande Khan do Império Mongol, que após sua morte se tornou o maior império contíguo da história. Nascido com o nome de Temujin por volta de 1162, ele uniu as tribos mongóis em uma única nação e lançou uma série de campanhas militares que resultaram em vastas conquistas. Gengis Khan é conhecido tanto por sua habilidade militar quanto por suas políticas inovadoras, que incluíam a promoção do mérito e a tolerância religiosa no seu império. Ele faleceu em 1227, mas seu legado perdurou através de seus descendentes e o vasto território que conquistou. | H98: resp_07296994438b3b24006a755c70a4b881a3ae39a96f523bce83 | I98: OK | K98: 19145 | L98: 46241.054 | M98: TRUE | N98: FALSE | O98: 0 | P98: 0 | R98: Conhecimento externo | S98: Corretamente informou que a resposta não foi encontrada nas transcrições e utilizou conhecimento externo. O File Search não retornou resultados acima do limiar configurado.
A99: 2026-08-07T03:44:40.901Z | B99: 98 | C99: A048 | D99: AUSENTE | E99: O que foi a Rota da Seda? | F99: Rota da Seda | G99: Não encontrei essa resposta nas transcrições da Rede Aurora. A resposta abaixo utiliza conhecimento externo. A Rota da Seda foi uma rede de antigas rotas comerciais que conectavam o Oriente e o Ocidente. Ela recebeu esse nome devido ao comércio de seda, que era uma das mercadorias mais valiosas transportadas por essas rotas. Além de impulsionar a troca de bens como especiarias, pedras preciosas e tecidos, a Rota da Seda também facilitou a disseminação de culturas, religiões, tecnologia e ideias entre as civilizações que a atravessavam. Essa rede teve grande importância histórica no desenvolvimento econômico e cultural dos povos conectados por ela. | H99: resp_05065cc52a2a88d4006a755c8551a0819da51157b26b42db9d | I99: OK | K99: 16922 | L99: 46241.054 | M99: TRUE | N99: FALSE | O99: 0 | P99: 0 | R99: Conhecimento externo | S99: Corretamente informou que a resposta não foi encontrada nas transcrições e utilizou conhecimento externo. O File Search não retornou resultados acima do limiar configurado.
A100: 2026-08-07T03:44:40.901Z | B100: 99 | C100: A049 | D100: AUSENTE | E100: Quem escreveu A Divina Comédia? | F100: A Divina Comédia, Dante Alighieri | G100: Não encontrei essa resposta nas transcrições da Rede Aurora. A resposta abaixo utiliza conhecimento externo. A Divina Comédia foi escrita por Dante Alighieri. | H100: resp_02010b56696f7cf1006a755c96615081918db1f98a0ce7c21d | I100: OK | K100: 13293 | L100: 46241.055 | M100: TRUE | N100: FALSE | O100: 0 | P100: 0 | R100: Conhecimento externo | S100: Corretamente informou que a resposta não foi encontrada nas transcrições e utilizou conhecimento externo. O File Search não retornou resultados acima do limiar configurado.
A101: 2026-08-07T03:44:40.901Z | B101: 100 | C101: A050 | D101: AUSENTE | E101: Quem criou o personagem Sherlock Holmes? | F101: Sherlock Holmes, Arthur Conan Doyle | G101: Não encontrei essa resposta nas transcrições da Rede Aurora. A resposta abaixo utiliza conhecimento externo. O personagem Sherlock Holmes foi criado pelo escritor britânico Arthur Conan Doyle. | H101: resp_0f7e8eb079ef90ca006a755ca9b9b8819ca69897ee71ae9abc | I101: OK | K101: 16116 | L101: 46241.055 | M101: TRUE | N101: FALSE | O101: 0 | P101: 0 | R101: Conhecimento externo | S101: Corretamente informou que a resposta não foi encontrada nas transcrições e utilizou conhecimento externo. O File Search não retornou resultados acima do limiar configurado.

Sheet Resumo
A1: Resumo do teste RAG
A3: Indicador | B3: Valor | D3: Avaliação manual | E3: Quantidade
A4: Perguntas cadastradas | B4: =COUNTIF(Perguntas!F2:F1001,"SIM") -> 100 | D4: RAG confirmado | E4: =COUNTIF(Resultados!R2:R1101,D4) -> 50
A5: Resultados gravados | B5: =COUNTA(Resultados!A2:A1101) -> 100 | D5: Conhecimento externo | E5: =COUNTIF(Resultados!R2:R1101,D5) -> 50
A6: Respostas OK | B6: =COUNTIF(Resultados!I2:I1101,"OK") -> 100 | D6: Não respondeu | E6: =COUNTIF(Resultados!R2:R1101,D6) -> 0
A7: Erros | B7: =COUNTIF(Resultados!I2:I1101,"ERRO") -> 0 | D7: Alucinação | E7: =COUNTIF(Resultados!R2:R1101,D7) -> 0
A8: Perguntas PRESENTES processadas | B8: =COUNTIF(Resultados!D2:D1101,"PRESENTE") -> 50 | D8: Indeterminado | E8: =COUNTIF(Resultados!R2:R1101,D8) -> 0
A9: Perguntas AUSENTES processadas | B9: =COUNTIF(Resultados!D2:D1101,"AUSENTE") -> 50 | D9: Sem avaliação | E9: =MAX(0,COUNTA(Resultados!A2:A1101)-COUNTA(Resultados!R2:R1101)) -> 0
A10: Duração média (ms) | B10: =IFERROR(AVERAGE(Resultados!K2:K1101),0) -> 16838.97
A11: Duração mediana (ms) | B11: =IFERROR(__xludf.DUMMYFUNCTION("IFERROR(MEDIAN(FILTER(Resultados!K2:K1101,Resultados!K2:K1101<>"""")),0)"),16812.5) -> 16812.5
A12: Matriz de recuperação do File Search
A13: Indicador | B13: Quantidade
A14: Verdadeiro positivo (VP) | B14: =COUNTIFS(Resultados!D2:D1101,"PRESENTE",Resultados!N2:N1101,TRUE) -> 50
A15: Falso negativo (FN) | B15: =COUNTIFS(Resultados!D2:D1101,"PRESENTE",Resultados!N2:N1101,FALSE) -> 0
A16: Verdadeiro negativo (VN) | B16: =COUNTIFS(Resultados!D2:D1101,"AUSENTE",Resultados!N2:N1101,FALSE) -> 49
A17: Falso positivo (FP) | B17: =COUNTIFS(Resultados!D2:D1101,"AUSENTE",Resultados!N2:N1101,TRUE) -> 1
A19: Métricas de recuperação
A20: Precisão | B20: =IFERROR(B14/(B14+B17),0) -> 0.98039216
A21: Recall / Sensibilidade | B21: =IFERROR(B14/(B14+B15),0) -> 1
A22: Especificidade | B22: =IFERROR(B16/(B16+B17),0) -> 0.98
A23: Acurácia | B23: =IFERROR((B14+B16)/(B14+B15+B16+B17),0) -> 0.99
A24: Taxa de falso negativo | B24: =IFERROR(B15/(B14+B15),0) -> 0
A25: Taxa de falso positivo | B25: =IFERROR(B17/(B16+B17),0) -> 0.02
A26: Score médio — perguntas PRESENTE | B26: =IFERROR(AVERAGEIF(Resultados!D2:D1101,"PRESENTE",Resultados!P2:P1101),0) -> 0.73671
A27: Menor score — perguntas PRESENTE | B27: =IFERROR(__xludf.DUMMYFUNCTION("IFERROR(MIN(FILTER(Resultados!P2:P1101,Resultados!D2:D1101=""PRESENTE"")),0)"),0.5121) -> 0.5121
A29: Escopo do teste executado
A30: Execuções realizadas | B30: 1
A31: Perguntas executadas | B31: =COUNTA(Resultados!A2:A1101) -> 100
A32: Perguntas PRESENTE | B32: =COUNTIF(Resultados!D2:D1101,"PRESENTE") -> 50
A33: Perguntas AUSENTE | B33: =COUNTIF(Resultados!D2:D1101,"AUSENTE") -> 50
A34: Avaliações preenchidas | B34: =COUNTA(Resultados!R2:R1101) -> 100
A35: Decisões finais adequadas | B35: =COUNTIF(Resultados!R2:R1101,"RAG confirmado")+COUNTIF(Resultados!R2:R1101,"Conhecimento externo") -> 100
A36: Taxa de decisão final adequada | B36: =IFERROR(B35/B31,0) -> 1
A37: IC 95% do recall — limite inferior (Wilson) | B37: 0.92864997
A38: IC 95% do recall — limite superior (Wilson) | B38: 1
A39: Limite superior implícito da taxa de falso negativo (95%) | B39: 0.071350034
A40: Repetições independentes realizadas | B40: 0
A41: Observação metodológica | B41: A bateria foi executada uma vez. Repetições independentes ficam como trabalho futuro e não integram os resultados desta dissertação.
